obiter/__init__.py
obiter/_modidx.py
obiter/canlii_api.py
obiter/wgnd.py
obiter-0.0.4.dist-info/LICENSE
obiter-0.0.4.dist-info/METADATA
obiter-0.0.4.dist-info/WHEEL
obiter-0.0.4.dist-info/entry_points.txt
obiter-0.0.4.dist-info/top_level.txt
obiter-0.0.4.dist-info/RECORD
