Metadata-Version: 2.1
Name: obiter
Version: 0.0.4
Summary: Computational research tools for lawyers
Home-page: https://github.com/simon-lawyer/obiter
Author: Simon Wallace
Author-email: simonwallace@osgoode.yorku.ca
License: Apache Software License 2.0
Keywords: legal lawyer research jupyter notebook python
Classifier: Development Status :: 4 - Beta
Classifier: Intended Audience :: Developers
Classifier: Natural Language :: English
Classifier: Programming Language :: Python :: 3.7
Classifier: Programming Language :: Python :: 3.8
Classifier: Programming Language :: Python :: 3.9
Classifier: Programming Language :: Python :: 3.10
Classifier: License :: OSI Approved :: Apache Software License
Requires-Python: >=3.7
License-File: LICENSE
Requires-Dist: fastcore
Requires-Dist: pandas
Requires-Dist: requests
Requires-Dist: seaborn
Provides-Extra: dev
